{
    "locales": {
        "en": {
            "title": "Contact",
            "title_long_prefix": "Don't hesitate to",
            "title_long": "**Contact** Me"
        }
    },
    "articles": [
        {
            "id": "contact_form",
            "component": "ArticleContactForm",
            "config": {},
            "locales": {
                "en": { "title": "Send me a **message**" }
            },
            "items": null
        },
        {
            "id": "contact_list",
            "component": "ArticleGrid",
            "config": {
                "format": "grid"
            },
            "locales": {
                "en": { "title": "Or if you **prefer**..." }
            },
            "items": [
                {
                    "value": "elonerajeev@gmail.com",
                    "links": [
                        { "href": "mailto:elonerajeev@gmail.com" }
                    ],
                    "icon": {
                        "fa": "fa-solid fa-envelope"
                    },
                    "locales": {
                        "en": { "title": "E-mail" }
                    }
                },
                {
                    "value": "linkedin.com/in/rajeev-kumar-2209b1243",
                    "links": [
                        { "href": "https://linkedin.com/in/rajeev-kumar-2209b1243" }
                    ],
                    "icon": {
                        "fa": "fa-brands fa-linkedin"
                    },
                    "locales": {
                        "en": { "title": "LinkedIn" }
                    }
                },
                {
                    "value": "github.com/elonerajeev",
                    "links": [
                        { "href": "https://github.com/elonerajeev" }
                    ],
                    "icon": {
                        "fa": "fa-brands fa-github"
                    },
                    "locales": {
                        "en": { "title": "GitHub" }
                    }
                },
                {
                    "value": "twitter.com/rajeev02030066",
                    "links": [
                        { "href": "https://twitter.com/rajeev02030066" }
                    ],
                    "icon": {
                        "fa": "fa-brands fa-twitter"
                    },
                    "locales": {
                        "en": { "title": "Twitter" }
                    }
                }
            ]
        }
    ]
}
